{
"type": "FeatureCollection",
"name": "waste",
"crs": { "type": "name", "properties": { "name": "urn:ogc:def:crs:OGC:1.3:CRS84" } },
"features": [
{ "type": "Feature", "properties": { "id": 1 }, "geometry": { "type": "Point", "coordinates": [ 40.61114166937962, -2.343748804935891 ] } },
{ "type": "Feature", "properties": { "id": 1 }, "geometry": { "type": "Point", "coordinates": [ 40.611212925403819, -2.344322767237694 ] } },
{ "type": "Feature", "properties": { "id": 1 }, "geometry": { "type": "Point", "coordinates": [ 40.610601388036891, -2.344613455523108 ] } },
{ "type": "Feature", "properties": { "id": 1 }, "geometry": { "type": "Point", "coordinates": [ 40.611105341360613, -2.345423637090284 ] } },
{ "type": "Feature", "properties": { "id": 1 }, "geometry": { "type": "Point", "coordinates": [ 40.612124888590387, -2.344360179493134 ] } },
{ "type": "Feature", "properties": { "id": 1 }, "geometry": { "type": "Point", "coordinates": [ 40.612172567788704, -2.344895701829763 ] } },
{ "type": "Feature", "properties": { "id": 1 }, "geometry": { "type": "Point", "coordinates": [ 40.612102593641652, -2.34544319626835 ] } },
{ "type": "Feature", "properties": { "id": 1 }, "geometry": { "type": "Point", "coordinates": [ 40.61285805588696, -2.344962965273846 ] } },
{ "type": "Feature", "properties": { "id": 1 }, "geometry": { "type": "Point", "coordinates": [ 40.612864470799501, -2.345427519377978 ] } },
{ "type": "Feature", "properties": { "id": 1 }, "geometry": { "type": "Point", "coordinates": [ 40.613180881677366, -2.344299777723132 ] } },
{ "type": "Feature", "properties": { "id": 1 }, "geometry": { "type": "Point", "coordinates": [ 40.614007535543017, -2.344337287465323 ] } },
{ "type": "Feature", "properties": { "id": 1 }, "geometry": { "type": "Point", "coordinates": [ 40.613966982165643, -2.344887706394782 ] } },
{ "type": "Feature", "properties": { "id": 1 }, "geometry": { "type": "Point", "coordinates": [ 40.612421270291833, -2.343723653472801 ] } },
{ "type": "Feature", "properties": { "id": 1 }, "geometry": { "type": "Point", "coordinates": [ 40.613018426341441, -2.343720003628627 ] } },
{ "type": "Feature", "properties": { "id": 1 }, "geometry": { "type": "Point", "coordinates": [ 40.613419722604284, -2.344793652544813 ] } }
]
}
